linktools_cntr/__init__.py
linktools_cntr/__main__.py
linktools_cntr/container.py
linktools_cntr/manager.py
linktools_cntr/metadata.py
linktools_cntr/repository.py
linktools_cntr/update.py
linktools_cntr/assets/containers/100-nginx/Dockerfile
linktools_cntr/assets/containers/100-nginx/compose.yml
linktools_cntr/assets/containers/100-nginx/container.py
linktools_cntr/assets/containers/100-nginx/default.conf
linktools_cntr/assets/containers/100-nginx/dnsapi.txt
linktools_cntr/assets/containers/100-nginx/http.conf
linktools_cntr/assets/containers/100-nginx/https.conf
linktools_cntr/assets/containers/110-portainer/compose.yml
linktools_cntr/assets/containers/110-portainer/container.py
linktools_cntr/assets/containers/120-flare/compose.yml
linktools_cntr/assets/containers/120-flare/container.py
linktools_cntr-0.0.4.dist-info/LICENSE
linktools_cntr-0.0.4.dist-info/METADATA
linktools_cntr-0.0.4.dist-info/WHEEL
linktools_cntr-0.0.4.dist-info/entry_points.txt
linktools_cntr-0.0.4.dist-info/top_level.txt
linktools_cntr-0.0.4.dist-info/RECORD
