Metadata-Version: 2.2
Name: linktools_cntr
Version: 0.0.4
Summary: linktools container toolkit
Author-email: Hu Ji <669898595@qq.com>
License: Apache-2.0
Project-URL: Homepage, https://github.com/ice-black-tea/linktools-cntr
Project-URL: Repository, https://github.com/ice-black-tea/linktools-cntr.git
Requires-Python: >=3.6
License-File: LICENSE
Requires-Dist: linktools
Requires-Dist: GitPython
Requires-Dist: jinja2
Requires-Dist: pyyaml
Requires-Dist: dotenv
Requires-Dist: linktools>=0.8.14
Dynamic: requires-dist
